std_daq_service/__init__.py
std_daq_service/protocol.py
std_daq_service/start_utils.py
std_daq_service/rest_v2/static/asset-manifest.json
std_daq_service/rest_v2/static/index.html
std_daq_service/rest_v2/static/manifest.json
std_daq_service/rest_v2/static/js/787.6a20824f.chunk.js
std_daq_service/rest_v2/static/js/787.6a20824f.chunk.js.map
std_daq_service/rest_v2/static/js/main.9c6e0ea6.js
std_daq_service/rest_v2/static/js/main.9c6e0ea6.js.LICENSE.txt
std_daq_service/rest_v2/static/js/main.9c6e0ea6.js.map
std_daq_service-1.1.1.dist-info/METADATA
std_daq_service-1.1.1.dist-info/WHEEL
std_daq_service-1.1.1.dist-info/entry_points.txt
std_daq_service-1.1.1.dist-info/top_level.txt
std_daq_service-1.1.1.dist-info/RECORD
