Metadata-Version: 2.1
Name: std-daq-service
Version: 1.1.1
Requires-Dist: std-buffer
Requires-Dist: pyzmq
Requires-Dist: pcaspy
Requires-Dist: opencv-python
Requires-Dist: tifffile
Requires-Dist: protobuf
Requires-Dist: flask
Requires-Dist: flask-cors
Requires-Dist: numpy
Requires-Dist: redis
Requires-Dist: fastapi
Requires-Dist: uvicorn
